realmrider/__init__.py
realmrider/auth/__init__.py
realmrider/auth/azure.py
realmrider-0.1.0.dist-info/LICENSE
realmrider-0.1.0.dist-info/METADATA
realmrider-0.1.0.dist-info/WHEEL
realmrider-0.1.0.dist-info/top_level.txt
realmrider-0.1.0.dist-info/RECORD
