Metadata-Version: 2.1
Name: realmrider
Version: 0.1.0
Summary: A simple OAuth2 client for all your needs
Home-page: https://github.com/bytesentinel-io/realmrider
Author: ByteSentinel.io
Author-email: dev@bytesentinel.io
Classifier: Programming Language :: Python :: 3
Classifier: License :: OSI Approved :: MIT License
Classifier: Operating System :: OS Independent
Requires-Python: >=3.7
License-File: LICENSE
Requires-Dist: fibertrace >=0.1.5
Requires-Dist: turborest >=0.1.7
